sanic_routing/__init__.py
sanic_routing/exceptions.py
sanic_routing/group.py
sanic_routing/line.py
sanic_routing/patterns.py
sanic_routing/route.py
sanic_routing/router.py
sanic_routing/tree.py
sanic_routing/utils.py
sanic_routing-21.12.0.dist-info/LICENSE
sanic_routing-21.12.0.dist-info/METADATA
sanic_routing-21.12.0.dist-info/WHEEL
sanic_routing-21.12.0.dist-info/top_level.txt
sanic_routing-21.12.0.dist-info/RECORD
