Metadata-Version: 2.1
Name: sanic-routing
Version: 21.12.0
Summary: Core routing component for Sanic
Home-page: https://github.com/sanic-org/sanic-routing/
Author: Adam Hopkins
Author-email: admhpkns@gmail.com
License: MIT
Platform: any
Classifier: Development Status :: 3 - Alpha
Classifier: Environment :: Web Environment
Classifier: License :: OSI Approved :: MIT License
Classifier: Programming Language :: Python :: 3.7
Classifier: Programming Language :: Python :: 3.8
Classifier: Programming Language :: Python :: 3.9
Classifier: Programming Language :: Python :: 3.10
License-File: LICENSE
